eats/__init__.py
eats/__version__.py
eats/application/__init__.py
eats/application/application.py
eats/behave/__init__.py
eats/behave/application_steps.py
eats/behave/cookies_steps.py
eats/behave/custom_types.py
eats/behave/deprecated_steps.py
eats/behave/driver_steps.py
eats/behave/element_steps.py
eats/behave/hooks.py
eats/behave/page_steps.py
eats/behave/screenshots_steps.py
eats/behave/user_steps.py
eats/common/__init__.py
eats/common/composite_element.py
eats/common/exceptions.py
eats/common/utils.py
eats/element/__init__.py
eats/element/checkbox.py
eats/element/element.py
eats/element/iframe.py
eats/element/input.py
eats/element/radio.py
eats/element/select.py
eats/page/__init__.py
eats/page/page.py
eats/page/react_page.py
eats/pyhamcrest/__init__.py
eats/pyhamcrest/arrayisequal.py
eats/pyhamcrest/arrayisequalbykey.py
eats/users/__init__.py
eats/users/users.py
eats/utils/__init__.py
eats/utils/bing.py
eats/utils/config.py
eats/utils/cropper.py
eats/utils/delayed_failures.py
eats/utils/google_site_verification.py
eats/utils/mapping.py
eats/utils/md5sum.py
eats/utils/naming.py
eats/utils/robots.py
eats/utils/root.py
eats/utils/screenshot.py
eats/utils/screenshots_dir.py
eats/utils/sitemap.py
eats/utils/var_envs.py
eats/utils/window.py
eats/utils/workspace.py
eats/utils/scripts/PageMaxHeight.js
eats/utils/scripts/PageScrollHeight.js
eats/utils/scripts/PageSize.js
eats/webdriver/__init__.py
eats/webdriver/webdriver.py
eats/webdriver/scripts/ElementCoordinates.js
eats/webdriver/scripts/FindByCssProperty.js
eats/webdriver/scripts/GetComputedStyle.js
eats/webdriver/scripts/GetGoogleTrackingKeys.js
etiqa_eats-0.11.2.23.dist-info/LICENSE.txt
etiqa_eats-0.11.2.23.dist-info/METADATA
etiqa_eats-0.11.2.23.dist-info/WHEEL
etiqa_eats-0.11.2.23.dist-info/top_level.txt
etiqa_eats-0.11.2.23.dist-info/RECORD
